setup.py
easy_expressions/__init__.py
easy_expressions.egg-info/PKG-INFO
easy_expressions.egg-info/SOURCES.txt
easy_expressions.egg-info/dependency_links.txt
easy_expressions.egg-info/requires.txt
easy_expressions.egg-info/top_level.txt